netpull/__init__.py
netpull/__main__.py
netpull/async_core.py
netpull/browsers.py
netpull/cli.py
netpull/config.py
netpull/cookie_handler.py
netpull/core.py
netpull/exceptions.py
netpull/extractors.py
netpull/result.py
netpull/utils.py
netpull-0.1.0.dist-info/licenses/LICENSE
netpull-0.1.0.dist-info/METADATA
netpull-0.1.0.dist-info/WHEEL
netpull-0.1.0.dist-info/entry_points.txt
netpull-0.1.0.dist-info/top_level.txt
netpull-0.1.0.dist-info/RECORD
