Metadata-Version: 2.4
Name: netpull
Version: 0.1.0
Summary: Web content extraction with screenshots and structured data
Author: NetPull Contributors
License: MIT
Project-URL: Homepage, https://github.com/netpull/netpull
Project-URL: Documentation, https://github.com/netpull/netpull#readme
Project-URL: Repository, https://github.com/netpull/netpull
Project-URL: Bug Tracker, https://github.com/netpull/netpull/issues
Keywords: web scraping,playwright,screenshot,html extraction,web automation
Classifier: Development Status :: 4 - Beta
Classifier: Intended Audience :: Developers
Classifier: License :: OSI Approved :: MIT License
Classifier: Programming Language :: Python :: 3
Classifier: Programming Language :: Python :: 3.8
Classifier: Programming Language :: Python :: 3.9
Classifier: Programming Language :: Python :: 3.10
Classifier: Programming Language :: Python :: 3.11
Classifier: Programming Language :: Python :: 3.12
Classifier: Topic :: Internet :: WWW/HTTP
Classifier: Topic :: Software Development :: Libraries :: Python Modules
Classifier: Topic :: Utilities
Requires-Python: >=3.8
License-File: LICENSE
Requires-Dist: playwright>=1.42.0
Requires-Dist: beautifulsoup4>=4.12.0
Requires-Dist: lxml>=4.9.0
Provides-Extra: dev
Requires-Dist: build>=0.10.0; extra == "dev"
Requires-Dist: twine>=4.0.0; extra == "dev"
Requires-Dist: pytest>=7.0.0; extra == "dev"
Requires-Dist: pytest-asyncio>=0.21.0; extra == "dev"
Dynamic: license-file
